<FASTOAD_model>
  <specifications>
    <MTOW units="kg" is_input="True">100.0</MTOW>
    <altitude units="m" is_input="True">0.0</altitude>
    <dISA units="degK" is_input="True">0.0</dISA>
    <distance>
      <climb units="m" is_input="True">0.0</climb>
      <forward units="m" is_input="True">17400.0</forward>
    </distance>
    <maxthrust>
      <k is_input="True">2.5</k>
    </maxthrust>
    <speed>
      <climb units="m/s" is_input="True">4.0</climb>
    </speed>
    <time>
      <hover units="min" is_input="True">0.0</hover>
    </time>
  </specifications>
  <data>
    <ESC>
      <efficiency is_input="True">0.95</efficiency>
      <mass units="kg" is_input="False">0.0017736932944015734<estimated units="kg" is_input="False">0.0017736932944015734</estimated></mass>
      <voltage units="V" is_input="False">11.052059085694403<estimated units="V" is_input="False">11.052059085694403</estimated></voltage>
      <constraints>
        <voltage is_input="False">0.25323925096659444</voltage>
        <power>
          <climb is_input="False">0.46423275151703863</climb>
          <forward is_input="False">0.5092305196916259</forward>
        </power>
      </constraints>
      <power>
        <climb units="W" is_input="False">25.682533041652217</climb>
        <forward units="W" is_input="False">23.525520512019774</forward>
        <max units="W" is_input="False">47.935989208696434<estimated units="W" is_input="False">47.935989208696434</estimated></max>
      </power>
      <reference>
        <mass units="kg" is_input="True">0.115</mass>
        <power units="W" is_input="True">3108.0</power>
        <voltage units="V" is_input="True">44.4</voltage>
      </reference>
      <settings>
        <mass>
          <k is_input="True">1.0336460989771392</k>
        </mass>
        <power>
          <k is_input="True">1.0000000000000002</k>
        </power>
        <voltage>
          <k is_input="True">1.8356860746114176</k>
        </voltage>
      </settings>
    </ESC>
    <avionics>
      <power units="W" is_input="True">0.0</power>
    </avionics>
    <battery>
      <capacity units="A*s" is_input="False">8460.189104333253<estimated units="A*s" is_input="False">8460.189104333253</estimated></capacity>
      <discharge_limit is_input="True">0.8</discharge_limit>
      <energy units="kJ" is_input="False">125.21079874413215<estimated units="kJ" is_input="False">125.21079874413215</estimated></energy>
      <mass units="kg" is_input="False">0.22740214177497062<estimated units="kg" is_input="False">0.22740214177497062</estimated></mass>
      <voltage units="V" is_input="False">14.8<estimated units="V" is_input="False">14.8</estimated><guess units="V" is_input="False">12.076549836549951</guess></voltage>
      <volume units="cm**3" is_input="False">104.32159652916813<estimated units="cm**3" is_input="False">104.32159652916813</estimated></volume>
      <cell>
        <number is_input="False">4.0<estimated is_input="False">4.0</estimated></number>
        <voltage units="V" is_input="False">3.7<estimated units="V" is_input="True">3.7</estimated></voltage>
      </cell>
      <constraints>
        <energy is_input="False">-7.015160816714245e-09</energy>
        <power>
          <climb is_input="False">0.9571201845746328</climb>
          <forward is_input="False">0.9640583395029346</forward>
          <takeoff is_input="False">0.8839383365247689</takeoff>
        </power>
        <voltage>
          <climb is_input="False">0.31041476303168125</climb>
          <forward is_input="False">0.36899645384097024</forward>
          <takeoff is_input="False">-1.1471066739130873e-09</takeoff>
        </voltage>
      </constraints>
      <current>
        <max units="A" is_input="False">117.50262644907296<estimated units="A" is_input="False">117.50262644907296</estimated></max>
      </current>
      <reference>
        <capacity units="A*s" is_input="True">12240.0</capacity>
        <mass units="kg" is_input="True">0.329</mass>
        <voltage units="V" is_input="True">14.8</voltage>
        <volume units="cm**3" is_input="True">150.93</volume>
        <current>
          <max units="A" is_input="True">170.0</max>
        </current>
      </reference>
    </battery>
    <gearbox>
      <mass units="kg" is_input="True">0.0</mass>
    </gearbox>
    <mission>
      <energy units="kJ" is_input="False">100.16863969800484<avionics units="kJ" is_input="False">0.0</avionics><climb units="kJ" is_input="False">0.0</climb><forward units="kJ" is_input="False">96.90468779864092</forward><hover units="kJ" is_input="False">0.0</hover><payload units="kJ" is_input="False">3.2639518993639163</payload></energy>
      <rho_air units="kg/m**3" is_input="False">1.2249908312368587</rho_air>
      <time units="min" is_input="False">25.839619203297673<climb units="min" is_input="False">0.0</climb><forward units="min" is_input="False">25.839619203297673</forward></time>
      <angle>
        <forward units="rad" is_input="False">0.22493688461750586</forward>
      </angle>
      <speed>
        <forward units="m/s" is_input="True">11.22307560797916</forward>
      </speed>
    </mission>
    <motor>
      <mass units="kg" is_input="False">0.015046950381587152<estimated units="kg" is_input="False">0.015046950381587152</estimated></mass>
      <resistance units="V/A" is_input="False">1.1970076125966373<estimated units="V/A" is_input="False">1.1970076125966373</estimated></resistance>
      <torque_coefficient units="N*m/A" is_input="False">0.009101080456651877<estimated units="N*m/A" is_input="False">0.009101080456651877</estimated></torque_coefficient>
      <current>
        <climb units="A" is_input="False">1.7353062865981228</climb>
        <forward units="A" is_input="False">1.5895621967580928</forward>
        <hover units="A" is_input="False">1.3473232152973174</hover>
        <takeoff units="A" is_input="False">3.2389181897767854</takeoff>
      </current>
      <length>
        <estimated units="m" is_input="False">0.02612619838116341</estimated>
      </length>
      <power>
        <climb units="W" is_input="False">17.71029563347442</climb>
        <forward units="W" is_input="False">14.844686868321471</forward>
        <hover units="W" is_input="False">11.480624353629947</hover>
        <takeoff units="W" is_input="False">47.93598926368412</takeoff>
      </power>
      <reference>
        <length units="m" is_input="True">0.088</length>
        <mass units="kg" is_input="True">0.575</mass>
        <resistance units="V/A" is_input="True">0.03</resistance>
        <torque_coefficient units="N*m/A" is_input="True">0.03</torque_coefficient>
        <torque>
          <friction units="N*m" is_input="True">0.03</friction>
          <max units="N*m" is_input="True">2.81714285714</max>
          <nominal units="N*m" is_input="True">2.32</nominal>
        </torque>
      </reference>
      <torque>
        <climb units="N*m" is_input="False">0.015008103850484856</climb>
        <forward units="N*m" is_input="False">0.013681675162769245</forward>
        <friction units="N*m" is_input="False">0.0007850582807784601<estimated units="N*m" is_input="False">0.0007850582807784601</estimated></friction>
        <hover units="N*m" is_input="False">0.011477038702757325</hover>
        <max units="N*m" is_input="False">0.040168562383333016<estimated units="N*m" is_input="False">0.040168562383333016</estimated></max>
        <nominal units="N*m" is_input="False">0.03307999255101368<estimated units="N*m" is_input="False">0.03307999255101368</estimated></nominal>
        <takeoff units="N*m" is_input="False">0.028692596756893316</takeoff>
      </torque>
      <voltage>
        <climb units="V" is_input="False">10.205861507131118</climb>
        <forward units="V" is_input="False">9.33885248315364</forward>
        <hover units="V" is_input="False">8.521061778851994</hover>
        <takeoff units="V" is_input="False">14.80000001697718</takeoff>
      </voltage>
      <constraints>
        <torque>
          <climb is_input="False">0.6263718948350486</climb>
          <forward is_input="False">0.6593934571966128</forward>
          <takeoff is_input="False">0.285695204048462</takeoff>
        </torque>
      </constraints>
      <settings>
        <speed>
          <k is_input="True">1.1056084020015309</k>
        </speed>
        <torque>
          <k is_input="True">2.882275943102493</k>
        </torque>
      </settings>
    </motor>
    <payload>
      <mass units="kg" is_input="True">0.22</mass>
      <power units="W" is_input="True">2.0</power>
    </payload>
    <propeller>
      <mass units="kg" is_input="False">0.0034315561443152244</mass>
      <number is_input="False">4.0</number>
      <advance_ratio>
        <climb is_input="True">0.16463767526149897</climb>
        <forward is_input="True">0.4999999999999997</forward>
      </advance_ratio>
      <geometry>
        <beta is_input="False">0.3<estimated is_input="True">0.3</estimated></beta>
        <diameter units="m" is_input="False">0.17088449908028136<estimated units="m" is_input="False">0.17088449908028136</estimated></diameter>
      </geometry>
      <power>
        <climb units="W" is_input="False">13.404581392372709</climb>
        <forward units="W" is_input="False">11.178757979640356</forward>
        <hover units="W" is_input="False">8.7118108123475</hover>
        <takeoff units="W" is_input="False">34.4364558893748</takeoff>
      </power>
      <reference>
        <diameter units="m" is_input="True">0.2794</diameter>
        <mass units="kg" is_input="True">0.014999</mass>
        <ND>
          <max units="m/s" is_input="True">44.45</max>
        </ND>
      </reference>
      <speed>
        <climb units="rad/s" is_input="False">893.1562258572495</climb>
        <forward units="rad/s" is_input="False">817.0606191601552</forward>
        <hover units="rad/s" is_input="False">759.0643403733153</hover>
        <takeoff units="rad/s" is_input="False">1200.1861030964908</takeoff>
      </speed>
      <thrust>
        <climb units="N" is_input="False">1.3675833108236268</climb>
        <forward units="N" is_input="False">1.3434297303648184</forward>
        <hover units="N" is_input="False">1.309586299242154</hover>
        <max units="N" is_input="False">3.273965748105385</max>
      </thrust>
      <torque>
        <climb units="N*m" is_input="False">0.015008103850484856</climb>
        <forward units="N*m" is_input="False">0.013681675162769245</forward>
        <hover units="N*m" is_input="False">0.011477038702757325</hover>
        <takeoff units="N*m" is_input="False">0.028692596756893316</takeoff>
      </torque>
      <aerodynamics>
        <CP>
          <axial is_input="False">0.026143539489528526<estimated is_input="False">0.026143539489528526</estimated></axial>
          <incidence is_input="False">0.028478960674176355<estimated is_input="False">0.028478960674176355</estimated></incidence>
          <static is_input="False">0.02768<estimated is_input="False">0.02768</estimated></static>
        </CP>
        <CT>
          <axial is_input="False">0.06479107002308437<estimated is_input="False">0.06479107002308437</estimated></axial>
          <incidence is_input="False">0.0760540975376172<estimated is_input="False">0.0760540975376172</estimated></incidence>
          <static is_input="False">0.0859<estimated is_input="False">0.0859</estimated></static>
        </CT>
      </aerodynamics>
      <constraints>
        <speed>
          <climb is_input="False">0.0001854215895791267</climb>
          <forward is_input="False">0.009999997335413792</forward>
          <max is_input="False">0.45351472312859775</max>
        </speed>
      </constraints>
      <settings>
        <ND>
          <k is_input="True">0.7343441336014637</k>
        </ND>
      </settings>
    </propeller>
    <system>
      <MTOW units="kg" is_input="False">0.5341625530468592</MTOW>
      <autonomy>
        <hover units="min" is_input="False">33.095175258509634</hover>
      </autonomy>
      <range>
        <max units="m" is_input="False">17399.9998779362</max>
        <min units="m" is_input="False">17399.9998779362</min>
      </range>
      <reference>
        <MTOW units="kg" is_input="True">1.4</MTOW>
      </reference>
      <constraints>
        <mass>
          <MTOW is_input="False">186.2089299963106</MTOW>
          <convergence is_input="False">-7.384708262393696e-10</convergence>
        </mass>
      </constraints>
      <settings>
        <MTOW>
          <k is_input="True">2.428011602965435</k>
        </MTOW>
      </settings>
    </system>
    <structure>
      <aerodynamics>
        <Cd is_input="True">1.0</Cd>
      </aerodynamics>
      <arms>
        <length units="m" is_input="False">0.12083358809933328</length>
        <mass units="kg" is_input="False">0.001653440818673866</mass>
        <number is_input="True">4.0</number>
        <prop_per_arm is_input="True">1.0</prop_per_arm>
        <diameter>
          <inner units="m" is_input="False">0.011233361907893645</inner>
          <outer units="m" is_input="False">0.01134683020999359</outer>
        </diameter>
        <material>
          <density units="kg/m**3" is_input="True">1700.0</density>
          <stress>
            <max units="N/m**2" is_input="True">70000000.0</max>
          </stress>
        </material>
        <settings>
          <diameter>
            <k is_input="True">0.9899999999999991</k>
          </diameter>
        </settings>
      </arms>
      <body>
        <mass units="kg" is_input="False">0.004098171171998796</mass>
        <surface>
          <front units="m**2" is_input="False">0.01052107858053903</front>
          <top units="m**2" is_input="False">0.023672426806212815</top>
        </surface>
      </body>
      <reference>
        <arms>
          <mass units="kg" is_input="True">0.14</mass>
        </arms>
        <body>
          <mass units="kg" is_input="True">0.347</mass>
          <surface>
            <front units="m**2" is_input="True">0.02</front>
            <top units="m**2" is_input="True">0.045</top>
          </surface>
        </body>
      </reference>
    </structure>
  </data>
</FASTOAD_model>
